Workbook
Name lstMembers: 'Paramètres'!$B$6:$B$13
Name lstCategories: 'Budget'!$B$6:$B$13

Sheet Lisez-moi
B2: Budget de projet
B3: Budget prévu par catégorie, dépenses réelles, financement et partage des frais entre les membres.
B5: Mode d’emploi
B6: 1. | C6: Dans « Budget », fixez le montant prévu de chaque catégorie et les sources de financement (cellules teintées).
B7: 2. | C7: Dans « Paramètres », listez les membres et leur part (1 = part égale, 2 = double part…).
B8: 3. | C8: Dans « Dépenses », une ligne par dépense : date, libellé, catégorie, montant, payé par.
B9: 4. | C9: « Budget » montre le reste par catégorie ; « Partage » qui doit recevoir et qui doit payer.
B11: Couleurs des cellules
B12: Paramètre | C12: À régler d’abord : date de début, membres, catégories…
B13: Saisie | C13: Cellules blanches : vos données, ligne par ligne.
B14: Calcul | C14: Cellules grises : calculées automatiquement, ne pas écraser.
B16: Bon à savoir
B17: · | C17: Montants en francs suisses (CHF). Les lignes livrées sont des exemples.
B18: · | C18: Solde positif : le membre a avancé plus que sa part et doit être remboursé.
B20: Modèle Halo · police Helvetica · nuance : Mise en page → Thèmes.

Sheet Budget
B2: Budget de projet
B3: Montants en CHF.
B5: Catégorie | C5: Prévu | D5: Dépensé | E5: Reste | F5: Utilisé
B6: Matériel | C6: 800 | D6: =IF(B6="","",SUMIFS(tDepenses[Montant CHF],tDepenses[Catégorie],B6)) | E6: =IF(B6="","",N(C6)-D6) | F6: =IF(OR(B6="",N(C6)=0),"",D6/C6)
B7: Logiciels | C7: 300 | D7: =IF(B7="","",SUMIFS(tDepenses[Montant CHF],tDepenses[Catégorie],B7)) | E7: =IF(B7="","",N(C7)-D7) | F7: =IF(OR(B7="",N(C7)=0),"",D7/C7)
B8: Déplacements | C8: 400 | D8: =IF(B8="","",SUMIFS(tDepenses[Montant CHF],tDepenses[Catégorie],B8)) | E8: =IF(B8="","",N(C8)-D8) | F8: =IF(OR(B8="",N(C8)=0),"",D8/C8)
B9: Communication | C9: 250 | D9: =IF(B9="","",SUMIFS(tDepenses[Montant CHF],tDepenses[Catégorie],B9)) | E9: =IF(B9="","",N(C9)-D9) | F9: =IF(OR(B9="",N(C9)=0),"",D9/C9)
B10: Imprévus | C10: 250 | D10: =IF(B10="","",SUMIFS(tDepenses[Montant CHF],tDepenses[Catégorie],B10)) | E10: =IF(B10="","",N(C10)-D10) | F10: =IF(OR(B10="",N(C10)=0),"",D10/C10)
D11: =IF(B11="","",SUMIFS(tDepenses[Montant CHF],tDepenses[Catégorie],B11)) | E11: =IF(B11="","",N(C11)-D11) | F11: =IF(OR(B11="",N(C11)=0),"",D11/C11)
D12: =IF(B12="","",SUMIFS(tDepenses[Montant CHF],tDepenses[Catégorie],B12)) | E12: =IF(B12="","",N(C12)-D12) | F12: =IF(OR(B12="",N(C12)=0),"",D12/C12)
D13: =IF(B13="","",SUMIFS(tDepenses[Montant CHF],tDepenses[Catégorie],B13)) | E13: =IF(B13="","",N(C13)-D13) | F13: =IF(OR(B13="",N(C13)=0),"",D13/C13)
B14: Total | C14: =SUM(C6:C13) | D14: =SUM(D6:D13) | E14: =C14-D14 | F14: =IF(C14=0,"",D14/C14)
B15: Hors catégorie | D15: =SUM(tDepenses[Montant CHF])-D14
B17: Financement
B18: Source | C18: Prévu | D18: Reçu
B19: Contribution des membres | C19: 600 | D19: 600
B20: Subvention [organisme] | C20: 1000 | D20: 0
B21: Sponsor [entreprise] | C21: 400 | D21: 400
B24: Total | C24: =SUM(C19:C23) | D24: =SUM(D19:D23)
B26: Solde
B27: Financement reçu − dépenses | C27: =D24-SUM(tDepenses[Montant CHF])
B28: Financement prévu − budget prévu | C28: =C24-C14

Sheet Dépenses
A1: Date | B1: Libellé | C1: Catégorie | D1: Montant CHF | E1: Payé par | F1: Justificatif | G1: Remarque
A2: 46283 | B2: Licence logiciel de maquettage | C2: Logiciels | D2: 144 | E2: Sam | F2: Oui
A3: 46290 | B3: Billets de train, visite du mandant | C3: Déplacements | D3: 87.6 | E3: Alex | F3: Oui
A4: 46297 | B4: Capteurs et câbles | C4: Matériel | D4: 236.4 | E4: Noa | F4: Oui
A5: 46301 | B5: Impression des affiches | C5: Communication | D5: 95 | E5: Alex | F5: Non
A6: 46304 | B6: Repas de l’équipe, atelier | C6: Imprévus | D6: 64.5 | E6: Sam | F6: Oui

Sheet Partage
B2: Partage des frais
B3: Chaque dépense est partagée selon les parts des membres.
B4: Total des dépenses | C4: =SUM(tDepenses[Montant CHF])
B5: Somme des parts | C5: =SUMIFS('Paramètres'!$C$6:$C$13,'Paramètres'!$B$6:$B$13,"<>")
B7: Membre | C7: A payé | D7: Sa part | E7: Solde | F7: À faire
B8: =IF('Paramètres'!$B$6="","",'Paramètres'!$B$6) | C8: =IF(B8="","",SUMIFS(tDepenses[Montant CHF],tDepenses[Payé par],B8)) | D8: =IF(OR(B8="",$C$5=0),"",$C$4*N('Paramètres'!$C$6)/$C$5) | E8: =IF(B8="","",C8-D8) | F8: =IF(B8="","",IF(ROUND(E8,2)>0,"reçoit ce montant",IF(ROUND(E8,2)<0,"paie ce montant","quitte")))
B9: =IF('Paramètres'!$B$7="","",'Paramètres'!$B$7) | C9: =IF(B9="","",SUMIFS(tDepenses[Montant CHF],tDepenses[Payé par],B9)) | D9: =IF(OR(B9="",$C$5=0),"",$C$4*N('Paramètres'!$C$7)/$C$5) | E9: =IF(B9="","",C9-D9) | F9: =IF(B9="","",IF(ROUND(E9,2)>0,"reçoit ce montant",IF(ROUND(E9,2)<0,"paie ce montant","quitte")))
B10: =IF('Paramètres'!$B$8="","",'Paramètres'!$B$8) | C10: =IF(B10="","",SUMIFS(tDepenses[Montant CHF],tDepenses[Payé par],B10)) | D10: =IF(OR(B10="",$C$5=0),"",$C$4*N('Paramètres'!$C$8)/$C$5) | E10: =IF(B10="","",C10-D10) | F10: =IF(B10="","",IF(ROUND(E10,2)>0,"reçoit ce montant",IF(ROUND(E10,2)<0,"paie ce montant","quitte")))
B11: =IF('Paramètres'!$B$9="","",'Paramètres'!$B$9) | C11: =IF(B11="","",SUMIFS(tDepenses[Montant CHF],tDepenses[Payé par],B11)) | D11: =IF(OR(B11="",$C$5=0),"",$C$4*N('Paramètres'!$C$9)/$C$5) | E11: =IF(B11="","",C11-D11) | F11: =IF(B11="","",IF(ROUND(E11,2)>0,"reçoit ce montant",IF(ROUND(E11,2)<0,"paie ce montant","quitte")))
B12: =IF('Paramètres'!$B$10="","",'Paramètres'!$B$10) | C12: =IF(B12="","",SUMIFS(tDepenses[Montant CHF],tDepenses[Payé par],B12)) | D12: =IF(OR(B12="",$C$5=0),"",$C$4*N('Paramètres'!$C$10)/$C$5) | E12: =IF(B12="","",C12-D12) | F12: =IF(B12="","",IF(ROUND(E12,2)>0,"reçoit ce montant",IF(ROUND(E12,2)<0,"paie ce montant","quitte")))
B13: =IF('Paramètres'!$B$11="","",'Paramètres'!$B$11) | C13: =IF(B13="","",SUMIFS(tDepenses[Montant CHF],tDepenses[Payé par],B13)) | D13: =IF(OR(B13="",$C$5=0),"",$C$4*N('Paramètres'!$C$11)/$C$5) | E13: =IF(B13="","",C13-D13) | F13: =IF(B13="","",IF(ROUND(E13,2)>0,"reçoit ce montant",IF(ROUND(E13,2)<0,"paie ce montant","quitte")))
B14: =IF('Paramètres'!$B$12="","",'Paramètres'!$B$12) | C14: =IF(B14="","",SUMIFS(tDepenses[Montant CHF],tDepenses[Payé par],B14)) | D14: =IF(OR(B14="",$C$5=0),"",$C$4*N('Paramètres'!$C$12)/$C$5) | E14: =IF(B14="","",C14-D14) | F14: =IF(B14="","",IF(ROUND(E14,2)>0,"reçoit ce montant",IF(ROUND(E14,2)<0,"paie ce montant","quitte")))
B15: =IF('Paramètres'!$B$13="","",'Paramètres'!$B$13) | C15: =IF(B15="","",SUMIFS(tDepenses[Montant CHF],tDepenses[Payé par],B15)) | D15: =IF(OR(B15="",$C$5=0),"",$C$4*N('Paramètres'!$C$13)/$C$5) | E15: =IF(B15="","",C15-D15) | F15: =IF(B15="","",IF(ROUND(E15,2)>0,"reçoit ce montant",IF(ROUND(E15,2)<0,"paie ce montant","quitte")))
B17: Le total des soldes vaut zéro : ce que les uns reçoivent, les autres le paient.

Sheet Paramètres
B2: Paramètres
B3: Membres et parts pour le partage des frais.
B5: Membre | C5: Part
B6: Alex | C6: 1
B7: Sam | C7: 1
B8: Noa | C8: 1
